LICENSE
LICENSE3
MANIFEST.in
README.rst
VERSION
pyproject.toml
setup.py
rom/__init__.py
rom/columns.py
rom/exceptions.py
rom/index.py
rom/model.py
rom/query.py
rom/util.py
rom.egg-info/PKG-INFO
rom.egg-info/SOURCES.txt
rom.egg-info/dependency_links.txt
rom.egg-info/pbr.json
rom.egg-info/requires.txt
rom.egg-info/top_level.txt
test/test_rom.py